sphinx_fediverse/__init__.py
sphinx_fediverse/package.json
sphinx_fediverse/py.typed
sphinx_fediverse/requirements.txt
sphinx_fediverse/sphinx_fediverse.py
sphinx_fediverse/_static/boost.svg
sphinx_fediverse/_static/fedi_layout.css
sphinx_fediverse/_static/fedi_script.min.js
sphinx_fediverse/_static/fedi_script_mastodon.min.js
sphinx_fediverse/_static/fedi_script_misskey.min.js
sphinx_fediverse/_static/like.svg
sphinx_fediverse/_static/marked.min.js
sphinx_fediverse/_static/purify.min.js
sphinx_fediverse-1.0.0.dist-info/licenses/LICENSE
sphinx_fediverse-1.0.0.dist-info/METADATA
sphinx_fediverse-1.0.0.dist-info/WHEEL
sphinx_fediverse-1.0.0.dist-info/top_level.txt
sphinx_fediverse-1.0.0.dist-info/RECORD
