Metadata-Version: 2.4
Name: sphinx-fediverse
Version: 1.0.0
Summary: Add fediverse comments to your Sphinx page
Author-email: Olivia Appleton-Crocker <liv@oliviaappleton.com>
License:                     GNU GENERAL PUBLIC LICENSE
Project-URL: Documentation, https://sphinx-fediverse.oliviaappleton.com
Project-URL: Source, https://github.com/LivInTheLookingGlass/sphinx-fediverse
Project-URL: Issues, https://github.com/LivInTheLookingGlass/sphinx-fediverse/issues
Keywords: sphinx,fediverse,comments,activitypub,mastodon,misskey
Classifier: Development Status :: 5 - Production/Stable
Classifier: Environment :: Console
Classifier: Environment :: Plugins
Classifier: Environment :: Web Environment
Classifier: Framework :: Sphinx
Classifier: Framework :: Sphinx :: Extension
Classifier: Intended Audience :: Developers
Classifier: License :: OSI Approved :: GNU General Public License v3 (GPLv3)
Classifier: Programming Language :: JavaScript
Classifier: Programming Language :: Python
Classifier: Programming Language :: Python :: 3
Classifier: Programming Language :: Python :: 3.7
Classifier: Programming Language :: Python :: 3.8
Classifier: Programming Language :: Python :: 3.9
Classifier: Programming Language :: Python :: 3.10
Classifier: Programming Language :: Python :: 3.11
Classifier: Programming Language :: Python :: 3.12
Classifier: Programming Language :: Python :: 3.13
Classifier: Programming Language :: Python :: 3.14
Classifier: Programming Language :: Python :: Implementation :: CPython
Classifier: Programming Language :: Python :: Implementation :: PyPy
Classifier: Topic :: Communications
Classifier: Topic :: Documentation
Classifier: Topic :: Documentation :: Sphinx
Classifier: Topic :: Internet
Classifier: Topic :: Internet :: WWW/HTTP :: Dynamic Content
Classifier: Topic :: Software Development :: Documentation
Requires-Python: >=3.7
License-File: LICENSE
Dynamic: license-file
